odoo/addons/account_move_line_sale_info/README.rst
odoo/addons/account_move_line_sale_info/__init__.py
odoo/addons/account_move_line_sale_info/__manifest__.py
odoo/addons/account_move_line_sale_info/hooks.py
odoo/addons/account_move_line_sale_info/i18n/account_move_line_sale_info.pot
odoo/addons/account_move_line_sale_info/i18n/es.po
odoo/addons/account_move_line_sale_info/i18n/es_AR.po
odoo/addons/account_move_line_sale_info/i18n/it.po
odoo/addons/account_move_line_sale_info/i18n/tr.po
odoo/addons/account_move_line_sale_info/models/__init__.py
odoo/addons/account_move_line_sale_info/models/account_move.py
odoo/addons/account_move_line_sale_info/models/sale_order_line.py
odoo/addons/account_move_line_sale_info/models/stock_move.py
odoo/addons/account_move_line_sale_info/readme/CONTRIBUTORS.md
odoo/addons/account_move_line_sale_info/readme/DESCRIPTION.md
odoo/addons/account_move_line_sale_info/readme/USAGE.md
odoo/addons/account_move_line_sale_info/security/account_security.xml
odoo/addons/account_move_line_sale_info/static/description/icon.png
odoo/addons/account_move_line_sale_info/static/description/index.html
odoo/addons/account_move_line_sale_info/tests/__init__.py
odoo/addons/account_move_line_sale_info/tests/test_account_move_line_sale_info.py
odoo/addons/account_move_line_sale_info/views/account_move_view.xml
odoo_addon_account_move_line_sale_info-18.0.1.0.0.4.dist-info/METADATA
odoo_addon_account_move_line_sale_info-18.0.1.0.0.4.dist-info/WHEEL
odoo_addon_account_move_line_sale_info-18.0.1.0.0.4.dist-info/top_level.txt
odoo_addon_account_move_line_sale_info-18.0.1.0.0.4.dist-info/RECORD
