Metadata-Version: 2.1
Name: odoo-addon-account_move_line_sale_info
Version: 18.0.1.0.0.4
Requires-Python: >=3.10
Requires-Dist: odoo-addon-account_move_line_stock_info==18.0.*
Requires-Dist: odoo==18.0.*
Summary: Introduces the purchase order line to the journal items
Home-page: https://github.com/OCA/account-financial-tools
License: AGPL-3
Author: ForgeFlow S.L., Odoo Community Association (OCA)
Author-email: support@odoo-community.org
Classifier: Programming Language :: Python
Classifier: Framework :: Odoo
Classifier: Framework :: Odoo :: 18.0
Classifier: License :: OSI Approved :: GNU Affero General Public License v3
